ncfs/NCFS.py
ncfs/__init__.py
ncfs/accelerated.py
ncfs/distances.py
ncfs-0.1.2.dist-info/LICENSE
ncfs-0.1.2.dist-info/METADATA
ncfs-0.1.2.dist-info/WHEEL
ncfs-0.1.2.dist-info/top_level.txt
ncfs-0.1.2.dist-info/RECORD
