Metadata-Version: 2.1
Name: ncfs
Version: 0.1.2
Summary: Python implementation of Neighborhood Component Feature Selection (NCFS)
Home-page: https://github.com/BradhamLab/ncfs
Author: Dakota Y. Hawkins
Author-email: dyh0110@bu.edu
License: BSD
Classifier: Programming Language :: Python :: 3
License-File: LICENSE
Requires-Dist: numpy
Requires-Dist: scipy
Requires-Dist: numba
Requires-Dist: scikit-learn
